linuxpy/__init__.py
linuxpy/configfs.py
linuxpy/constants.py
linuxpy/ctypes.py
linuxpy/device.py
linuxpy/io.py
linuxpy/ioctl.py
linuxpy/kernel.py
linuxpy/led.py
linuxpy/magic.py
linuxpy/mounts.py
linuxpy/proc.py
linuxpy/statfs.py
linuxpy/sysfs.py
linuxpy/thermal.py
linuxpy/types.py
linuxpy/util.py
linuxpy/codegen/__init__.py
linuxpy/codegen/base.py
linuxpy/codegen/cli.py
linuxpy/codegen/gpio.py
linuxpy/codegen/input.py
linuxpy/codegen/magic.py
linuxpy/codegen/midi.py
linuxpy/codegen/usbfs.py
linuxpy/codegen/usbids.py
linuxpy/codegen/video.py
linuxpy/gpio/__init__.py
linuxpy/gpio/config.py
linuxpy/gpio/device.py
linuxpy/gpio/raw.py
linuxpy/gpio/sim.py
linuxpy/input/__init__.py
linuxpy/input/cli.py
linuxpy/input/device.py
linuxpy/input/raw.py
linuxpy/midi/__init__.py
linuxpy/midi/cli.py
linuxpy/midi/device.py
linuxpy/midi/raw.py
linuxpy/usb/__init__.py
linuxpy/usb/base.py
linuxpy/usb/core.py
linuxpy/usb/lsusb.py
linuxpy/usb/raw.py
linuxpy/usb/usbfs.py
linuxpy/usb/usbsys.py
linuxpy/usb/ids/__init__.py
linuxpy/usb/ids/audio_terminal.py
linuxpy/usb/ids/base.py
linuxpy/usb/ids/bias.py
linuxpy/usb/ids/country.py
linuxpy/usb/ids/hid.py
linuxpy/usb/ids/hid_item.py
linuxpy/usb/ids/hid_usage.py
linuxpy/usb/ids/klass.py
linuxpy/usb/ids/language.py
linuxpy/usb/ids/phy.py
linuxpy/usb/ids/vendor.py
linuxpy/usb/ids/video_terminal.py
linuxpy/video/__init__.py
linuxpy/video/device.py
linuxpy/video/qt.py
linuxpy/video/raw.py
linuxpy/video/util.py
linuxpy-0.23.0.dist-info/licenses/LICENSE
linuxpy-0.23.0.dist-info/METADATA
linuxpy-0.23.0.dist-info/WHEEL
linuxpy-0.23.0.dist-info/entry_points.txt
linuxpy-0.23.0.dist-info/top_level.txt
linuxpy-0.23.0.dist-info/RECORD
