Metadata-Version: 2.4
Name: linuxpy
Version: 0.23.0
Summary: Human friendly interface to linux subsystems using python
Author-email: Jose Tiago Macara Coutinho <coutinhotiago@gmail.com>
License-Expression: GPL-3.0-or-later
Project-URL: Documentation, https://tiagocoutinho.github.io/linuxpy/
Project-URL: Homepage, https://github.com/tiagocoutinho/linuxpy
Project-URL: Repository, https://github.com/tiagocoutinho/linuxpy
Keywords: linux,video,system,midi,gpio,led,input,gamepad,joystick,keyboard,mouse,thermal,asyncio
Classifier: Development Status :: 4 - Beta
Classifier: Intended Audience :: Developers
Classifier: Intended Audience :: System Administrators
Classifier: Operating System :: POSIX :: Linux
Classifier: Programming Language :: Python :: 3
Classifier: Programming Language :: Python :: 3.10
Classifier: Programming Language :: Python :: 3.11
Classifier: Programming Language :: Python :: 3.12
Classifier: Programming Language :: Python :: 3.13
Classifier: Programming Language :: Python :: 3.14
Classifier: Topic :: Multimedia :: Video
Classifier: Topic :: Multimedia :: Video :: Capture
Requires-Python: >=3.10
License-File: LICENSE
Requires-Dist: typing_extensions<5,>=4.6; python_version < "3.12"
Provides-Extra: dev
Requires-Dist: build>=0.10.0; extra == "dev"
Requires-Dist: gevent>=21; extra == "dev"
Requires-Dist: twine>=4.0.2; extra == "dev"
Requires-Dist: pytest>=8.1; extra == "dev"
Requires-Dist: pytest-asyncio>=1.0.0; extra == "dev"
Requires-Dist: pytest-cov>=6; extra == "dev"
Requires-Dist: ruff>=0.3.0; extra == "dev"
Requires-Dist: numpy>=1.1; extra == "dev"
Provides-Extra: examples
Requires-Dist: flask<4,>=2; extra == "examples"
Requires-Dist: fastapi<1; extra == "examples"
Requires-Dist: opencv-python; extra == "examples"
Requires-Dist: qtpy; extra == "examples"
Requires-Dist: pyqt6; extra == "examples"
Requires-Dist: gunicorn; extra == "examples"
Requires-Dist: gevent; extra == "examples"
Requires-Dist: uvicorn; extra == "examples"
Requires-Dist: numpy; extra == "examples"
Requires-Dist: Pillow; extra == "examples"
Provides-Extra: docs
Requires-Dist: mkdocs; extra == "docs"
Requires-Dist: mkdocs-material; extra == "docs"
Requires-Dist: mkdocstrings[python]; extra == "docs"
Requires-Dist: pygments; extra == "docs"
Requires-Dist: pymdown-extensions; extra == "docs"
Requires-Dist: mkdocs-coverage; extra == "docs"
Dynamic: license-file
